Workbook

Sheet Sheet1
A1: Scenario | B1: est_growth | C1: =2025 -> 2025 | D1: =C1+1 -> 2026 | E1: =D1+1 -> 2027 | F1: =E1+1 -> 2028 | G1: =F1+1 -> 2029 | H1: =G1+1 -> 2030 | I1: =H1+1 -> 2031 | J1: =I1+1 -> 2032 | K1: =J1+1 -> 2033
A2: Baseline: no growth in patient revenues | B2: =0 -> 0 | D2: 0 | E2: 0 | F2: 239.13125 | G2: 557.97292 | H2: 876.81458 | I2: 1195.6562 | J2: 1514.4979 | K2: 1594.2083
A3: Modest growth in patient revenues | B3: =0.03 -> 0.03 | D3: 0 | E3: 0 | F3: 261.30517 | G3: 628.00343 | H3: 1016.4684 | I3: 1427.6761 | J3: 1862.6414 | K3: 2019.4954
A4: Modest contraction in patient revenues | B4: =-0.03 -> -0.03 | D4: 0 | E4: 0 | F4: 218.24864 | G4: 493.96941 | H4: 752.95052 | I4: 995.94818 | J4: 1223.6883 | K4: 1249.4502

Sheet Logic_Model
A1: Back of Envelope
A2: What is OBBA impact on state's ability to levy and collect provider taxes?
A3: All $ amounts are in millions of nominal dollars
A5: Tax Revenues
A6: FY 2025 MCO assessments | B6: 1821.5 | C6: https://illinoiscomptroller.gov/financial-reports-data/revenues-state-income/revenue-source?RevSel=2683&RevGrpSel=0&RevClsSel=0&RevTypeSel=0&FY=25&GroupBy=None&GetQueryData=Search
A7: FY 2025 Hospital Assessments | B7: 2004.6 | C7: https://illinoiscomptroller.gov/financial-reports-data/revenues-state-income/revenue-source?RevSel=0133&RevGrpSel=0&RevClsSel=0&RevTypeSel=0&FY=25&GroupBy=None&GetQueryData=Search
A8: Total | B8: =SUM(B6:B7) -> 3826.1
A9: NB: FF figure for total in FY 2025? | B9: 4712.6279 | C9: https://github.com/AleaWM/Fiscal-Futures/blob/main/data/FY2025%20Files/summary_file_FY25_PensionChange_2025_07_016.xlsx
A10: FY 2025 Healthcare Provider Supplemental Assessment | B10: =For_Alea!$E$10 -> 886.54 | C10: See "For_Alea" tab of this spreadsheet; I think this is the County Hospital Assessment
A12: MCO and Hospital Assessments only | B12: =B8 -> 3826.1
A13: Alternative assumption: adding in the county hosp assessment | B13: =B8+B10 -> 4712.64
A15: Our assumed value for FY 2025 | B15: =B12 -> 3826.1
A17: Tax Base
A18: What is the "tax base" here?
A19: We know $ per bed-day, $ per member--but we want a dollar number "kind of like" net patient revenues
A20: We know that Illinois has among the highest provider taxes & assessments, but we don't know specifics
A21: Assumed tax rates for hospital and MCO assessments: | B21: =0.06 -> 0.06 | C21: why? Because KFF survey says "between 3.5% and 5.5" for hospitals; no info on MCO assessments (Burns, Alice, Elizabeth Hinton, Elizabeth Williams, and Robin Rudowitz. “5 Key Facts About Medicaid and Provider Taxes.” KFF (blog), March 26, 2025. https://www.kff.org/medicaid/issue-brief/5-key-facts-about-medicaid-and-provider-taxes/.)
A22: Implied tax base in SFY 2025 | B22: =B15/B21 -> 63768.333 | C22: calculated as tax revenues/tax rate
A24: Growth & Timing
A25: Date at which first 0.5 pp reduction must occur | B25: 46661
A26: State fiscal year in which 0.5 pp reduction must occur | B26: =2028 -> 2028
A27: What share of that fiscal year will be affected by that reduction? | B27: =0.75 -> 0.75
A28: Assumed annual growth rate in tax base | B28: =0 -> 0 | C28: my assumption: low, but "surely" decreased Medicaid enrollments & increased uninsured will push utilization, hence the "revenue base", down?
A29: What is tax base in that first year? | B29: =(1+$B$28)^3*B22 -> 63768.333 | C29: 3 years, from SFY 2025 to SFY 2028
A31: Tax Revenues in the First Affected State Fiscal Year (2028)
A32: First 3 months of the year (no reduction) | B32: =B21*B29/4 -> 956.525
A33: Last 9 months of the year (with reduction of 0.5 pp in tax rate) | B33: =B29*(B21-0.005)*3/4 -> 2630.4438
A34: Total | B34: =SUM(B32:B33) -> 3586.9688
A36: Loss in Tax Revenues Relative to Status Quo in SFY 2028
A37: Counterfactual status quo | B37: =B21*B29 -> 3826.1
A38: Under OBBB | B38: =B34 -> 3586.9688
A39: Difference | B39: =B37-B38 -> 239.13125

Sheet Revenue_Forecasts
A1: Assumed annual growth in tax base | B1: =0.08 -> 0.08
A2: Assumed current tax rate | B2: =Logic_Model!$B$21 -> 0.06
A4: State Fiscal Year | C4: =2025 -> 2025 | D4: =C4+1 -> 2026 | E4: =D4+1 -> 2027 | F4: =E4+1 -> 2028 | G4: =F4+1 -> 2029 | H4: =G4+1 -> 2030 | I4: =H4+1 -> 2031 | J4: =I4+1 -> 2032 | K4: =J4+1 -> 2033
A5: Provider Tax Revenues: Actual | C5: =Logic_Model!$B$15 -> 3826.1
A6: Implied Tax Base | C6: =Logic_Model!$B$22 -> 63768.333 | D6: =C6*(1+$B$1) -> 68869.8 | E6: =D6*(1+$B$1) -> 74379.384 | F6: =E6*(1+$B$1) -> 80329.735 | G6: =F6*(1+$B$1) -> 86756.113 | H6: =G6*(1+$B$1) -> 93696.603 | I6: =H6*(1+$B$1) -> 101192.33 | J6: =I6*(1+$B$1) -> 109287.72 | K6: =J6*(1+$B$1) -> 118030.73
A7: Provider Tax Revenues: Counterfactual, no OBBB | D7: =Logic_Model!$B$21*D6 -> 4132.188 | E7: =Logic_Model!$B$21*E6 -> 4462.763 | F7: =Logic_Model!$B$21*F6 -> 4819.7841 | G7: =Logic_Model!$B$21*G6 -> 5205.3668 | H7: =Logic_Model!$B$21*H6 -> 5621.7962 | I7: =Logic_Model!$B$21*I6 -> 6071.5398 | J7: =Logic_Model!$B$21*J6 -> 6557.263 | K7: =Logic_Model!$B$21*K6 -> 7081.8441
A9: Tax rate, July 1-September 30 | C9: =Logic_Model!$B$21 -> 0.06 | D9: =Logic_Model!$B$21 -> 0.06 | E9: =Logic_Model!$B$21 -> 0.06 | F9: =E10 -> 0.06 | G9: =F10 -> 0.055 | H9: =G10 -> 0.05 | I9: =H10 -> 0.045 | J9: =I10 -> 0.04 | K9: =J10 -> 0.035
A10: Tax rate, October 1 -June 30 | C10: =Logic_Model!$B$21 -> 0.06 | D10: =Logic_Model!$B$21 -> 0.06 | E10: =Logic_Model!$B$21 -> 0.06 | F10: =F9-0.005 -> 0.055 | G10: =G9-0.005 -> 0.05 | H10: =H9-0.005 -> 0.045 | I10: =I9-0.005 -> 0.04 | J10: =J9-0.005 -> 0.035 | K10: =K9 -> 0.035
A11: Provider Tax Revenues with OBBB reductions | D11: =D6*(D9/4 + D10*3/4) -> 4132.188 | E11: =E6*(E9/4 + E10*3/4) -> 4462.763 | F11: =F6*(F9/4 + F10*3/4) -> 4518.5476 | G11: =G6*(G9/4 + G10*3/4) -> 4446.2508 | H11: =H6*(H9/4 + H10*3/4) -> 4333.4679 | I11: =I6*(I9/4 + I10*3/4) -> 4174.1836 | J11: =J6*(J9/4 + J10*3/4) -> 3961.6798 | K11: =K6*(K9/4 + K10*3/4) -> 4131.0757
A13: Loss in Revenues relative to status quo | D13: =D7-D11 -> 0 | E13: =E7-E11 -> 0 | F13: =F7-F11 -> 301.23651 | G13: =G7-G11 -> 759.11599 | H13: =H7-H11 -> 1288.3283 | I13: =I7-I11 -> 1897.3562 | J13: =J7-J11 -> 2595.5833 | K13: =K7-K11 -> 2950.7684
A15: Nice Table: Loss in Revenues relative to status quo: Based on MCO and Hospital Assessments Only
A16: State Fiscal Year | C16: =2025 -> 2025 | D16: =C16+1 -> 2026 | E16: =D16+1 -> 2027 | F16: =E16+1 -> 2028 | G16: =F16+1 -> 2029 | H16: =G16+1 -> 2030 | I16: =H16+1 -> 2031 | J16: =I16+1 -> 2032 | K16: =J16+1 -> 2033
A17: Assumed annual growth rate of tax base (patient revenues)
A18: Baseline: no growth in patient revenues | B18: =0 -> 0 | D18: 0 | E18: 0 | F18: 239.13125 | G18: 557.97292 | H18: 876.81458 | I18: 1195.6562 | J18: 1514.4979 | K18: 1594.2083
A19: Modest growth in patient revenues | B19: =0.03 -> 0.03 | D19: 0 | E19: 0 | F19: 261.30517 | G19: 628.00343 | H19: 1016.4684 | I19: 1427.6761 | J19: 1862.6414 | K19: 2019.4954
A20: Modest contraction in patient revenues | B20: =-0.03 -> -0.03 | D20: 0 | E20: 0 | F20: 218.24864 | G20: 493.96941 | H20: 752.95052 | I20: 995.94818 | J20: 1223.6883 | K20: 1249.4502
K26: For Internal Use: Comparing Our Numbers to GOMB Report ($ millions)
K28: State Fiscal Year | L28: =F16 -> 2028 | M28: =G16 -> 2029 | N28: =H16 -> 2030 | O28: =I16 -> 2031 | P28: =J16 -> 2032 | Q28: =K16 -> 2033
K29: Impact on State Revenues Only
K30: FF estimates
K31: =A18 -> Baseline: no growth in patient revenues | L31: 239.13125 | M31: 557.97292 | N31: 876.81458 | O31: 1195.6562 | P31: 1514.4979 | Q31: 1594.2083
K32: =A19 -> Modest growth in patient revenues | L32: 261.30517 | M32: 628.00343 | N32: 1016.4684 | O32: 1427.6761 | P32: 1862.6414 | Q32: 2019.4954
K33: =A20 -> Modest contraction in patient revenues | L33: 218.24864 | M33: 493.96941 | N33: 752.95052 | O33: 995.94818 | P33: 1223.6883 | Q33: 1249.4502
K34: NEW: ASSUMING LARGE GROWTH (8%) | L34: 301.23651 | M34: 759.11599 | N34: 1288.3283 | O34: 1897.3562 | P34: 2595.5833 | Q34: 2950.7684
K35: GOMB estimates (ballparking!) | L35: =L36+L37 -> 304 | M35: =M36+M37 -> 756 | N35: =N36+N37 -> 1226 | O35: =O36+O37 -> 1694
K36: MCO | L36: 150 | M36: 349 | N36: 549 | O36: 748
K37: Hospital Assessment | L37: 154 | M37: 407 | N37: 677 | O37: 946
K40: Including Federal Matching Revenues
K41: Assumed FMAP value for FF calculations | L41: =L48 -> 0.62 | M41: =M48 -> 0.622 | N41: =N48 -> 0.62276923 | O41: =O48 -> 0.62355556 | P41: =$O$41 -> 0.62355556 | Q41: =$O$41 -> 0.62355556
K42: =K30 -> FF estimates
K43: =K31 -> Baseline: no growth in patient revenues | L43: =L31/(1-L$41) -> 629.29276 | M43: =M31/(1-M$41) -> 1476.1188 | N43: =N31/(1-N$41) -> 2324.3453 | O43: =O31/(1-O$41) -> 3176.1825 | P43: =P31/(1-P$41) -> 4023.1645 | Q43: =Q31/(1-Q$41) -> 4234.91
K44: =K32 -> Modest growth in patient revenues | L44: =L32/(1-L$41) -> 687.64519 | M44: =M32/(1-M$41) -> 1661.3847 | N44: =N32/(1-N$41) -> 2694.5533 | O44: =O32/(1-O$41) -> 3792.528 | P44: =P32/(1-P$41) -> 4947.9848 | Q44: =Q32/(1-Q$41) -> 5364.6573
K45: =K33 -> Modest contraction in patient revenues | L45: =L33/(1-L$41) -> 574.33851 | M45: =M33/(1-M$41) -> 1306.7974 | N45: =N33/(1-N$41) -> 1995.9944 | O45: =O33/(1-O$41) -> 2645.6711 | P45: =P33/(1-P$41) -> 3250.6479 | Q45: =Q33/(1-Q$41) -> 3319.0826
K46: =K35 -> GOMB estimates (ballparking!) | L46: =800 -> 800 | M46: =2000 -> 2000 | N46: =3250 -> 3250 | O46: =4500 -> 4500
K47: GOMB implied federal $ only | L47: =L46-L35 -> 496 | M47: =M46-M35 -> 1244 | N47: =N46-N35 -> 2024 | O47: =O46-O35 -> 2806
K48: GOMB implied "FMAP" | L48: =L47/L46 -> 0.62 | M48: =M47/M46 -> 0.622 | N48: =N47/N46 -> 0.62276923 | O48: =O47/O46 -> 0.62355556
K50: Side bar: GOMB says (p. 9) this for 2033 | P50: NB: for 2032 and 2033, I use the 2031 FMAP
K51: Total impact ($ billion) | L51: 6.1
K52: Federal matching $ (billion) | L52: 3.8
K53: Implied FMAP | L53: =L52/L51 -> 0.62295082

Sheet For_Alea
A1: Exploring full list of tax/assessment revenues
A2: Millions of $
A4: Name | B4: Code | C4: FY 2023 | D4: FY 2024 | E4: FY 2025 | F4: Comment | H4: Sidebar on Related Funds
A5: Comptroller Data | H5: Fund # | I5: Page of "Facts on Funds" | J5: FY2023 Rev ($ mil) | K5: Fund Name
A6: MCO Provider Assessment | B6: 2683 | C6: 1446.976 | D6: 1588.2909 | E6: 1821.5 | H6: 344 | I6: 316 | J6: 53.64715 | K6: Care Provider Fund for Persons with a DD
A7: Health Care Provider Tax | B7: 133 | C7: 1872.2033 | D7: =1931.945387 -> 1931.9454 | E7: 2004.5733 | H7: 329 | I7: 300 | J7: 2946.643 | K7: County Provider Trust Fund
A8: LTC Provider Assessments | B8: 2374 | C8: 272.13896 | D8: 298.9645 | E8: =331.44791 -> 331.44791 | F8: Tax Handbook refers to these as nursing home assessments (2025, p. 50) | H8: 793 | I8: 646 | J8: 13518.791 | K8: Healthcare Provider Relief Fund
A9: Hospital License Fees | B9: 2495 | C9: =1.55397 -> 1.55397 | D9: =1.57399 -> 1.57399 | E9: =1.534335 -> 1.534335 | H9: 68 | I9: 88 | J9: 1.789533 | K9: Hospital Licensure Fund
A10: Health Care Pro Sup Fee (?) | B10: 129 | C10: 769.2006 | D10: 821.35752 | E10: 886.54 | H10: 346 | I10: 318 | J10: 4749.3637 | K10: Hospital Provider Fund
A11: Total | C11: =SUM(C6:C10) -> 4362.0729 | D11: =SUM(D6:D10) -> 4642.1323 | E11: =SUM(E6:E10) -> 5045.5955 | H11: 345 | I11: 317 | J11: 784.35011 | K11: LTC Provider Fund
A12: FF Data
A13: FF figure for total | C13: 4088.3799 | D13: 4341.5937 | E13: 4712.6279
A14: Diff between Comptroller & FF totals | C14: =C11-C13 -> 273.69293 | D14: =D11-D13 -> 300.53859 | E14: =E11-E13 -> 332.96766
A15: If I pull out LTC provider $ from Comptroller, I get very close to FF | C15: =C11-C8 -> 4089.9339 | D15: =D11-D8 -> 4343.1678 | E15: =E11-E8 -> 4714.1476
A16: If I also pull out Hospital License Fees, I nail it | C16: =C15-C9 -> 4088.3799 | D16: =D15-D9 -> 4341.5938 | E16: =E15-E9 -> 4712.6133
A17: Revised Diff | C17: =C16-C13 -> 8.9999958e-08 | D17: =D16-D13 -> 9.981e-05 | E17: =E16-E13 -> -0.01458847
A18: Other Sources/Questions
A19: Tax Handbook, 2025, p. 51 | C19: 4361 | D19: 4641 | F19: Same figures as from TBFR below
A20: Developmentally disabled assessment? | F20: Tax Handbook refers to these (2025, p. 50)
A21: County hospital services assessment? | F21: Tax Handbook describes as levied on Cook County (2025, p. 50)
A23: Snapshot of p. 14 from 2024 TBFR
A40: Sources
A41: Commission on Government Forecasting and Accountability. “Illinois Tax Handbook for Legislators, 41st Edition,” April 2025. https://cgfa.ilga.gov/commission/lru/TaxHandbook2025.pdf.
A42: Comptroller, State of Illinois. “Traditional Budgetary Financial Report FY 2024,” December 2024. https://illinoiscomptroller.gov/__media/sites/comptroller/FY%202024%20Traditional%20Budgetary_Final.pdf.
A43: Commission on Government Forecasting & Accountability. “Facts on Funds,” January 2024. https://cgfa.ilga.gov/Upload/JAN%202024%20Facts%20on%20Funds.pdf.

Sheet Sankey_Alea
A1: FY 2025 Assessments ($ millions)
C2: Target | D2: Fund # | E2: Amount
A3: MCO assessments | B3: 1821.5 | C3: County Provider Trust | D3: 0329 | E3: 372.821
C4: Healthcare Provider Relief | D4: 0793 | E4: 1448.6936
A5: Healthcare Provider Supplemental Assessment | B5: 886.54 | C5: County Provider Trust | D5: 0329 | E5: 886.54
A6: Healthcare Provider Tax | B6: 2004.6 | C6: Care Providers for Persons with DD | D6: 0344 | E6: 23.345964
C7: Hospital Providers | D7: 0346 | E7: 1981.2273
A9: Total | B9: =SUM(B3:B6) -> 4712.64 | E9: =SUM(E3:E7) -> 4712.6279
A12: Source | B12: Target | C12: Amount
A13: MCO Assessments | B13: County Provider Trust | C13: 372.821
A14: MCO Assessments | B14: Healthcare Provider Relief | C14: 1448.6936
A15: Healthcare Provider Supplemental Assessment | B15: County Provider Trust | C15: 886.54
A16: Healthcare Provider Tax | B16: Care Providers for Persons with DD | C16: 23.345964
A17: Healthcare Provider Tax | B17: Hospital Providers | C17: 1981.2273
