Workbook

Sheet fred_data_for_index
A1: year | B1: ILNGSP | C1: CPIAUCSL | D1: WPSFD49406 | E1: ILPOP | F1: expenditure_nominal | G1: revenue_nominal | H1: fiscal_gap_nominal | I1: expenditure_share_gsp | J1: revenue_share_gsp | K1: fiscal_gap_gsp | L1: expenditure_adjusted_cpi | M1: revenue_adjusted_cpi | N1: fiscal_gap_adjusted_cpi | O1: nominal_exp_perperson | P1: nominal_rev_perperson | Q1: fiscal_gap_perperson | R1: A829RD3Q086SBEA | S1: exp_adj_sbea | T1: rev_adj_sbea | U1: fiscal_gap_sbea | V1: exp_adj_wpsfd | W1: rev_adj_wpsfd
A2: 1998 | B2: 436533.4 | C2: 162 | E2: 12069.774 | F2: ='Fiscal Gap'!B2 -> 31241.142 | G2: ='Fiscal Gap'!C2 -> 32028.332 | H2: =Table1[[#This Row],[revenue_nominal]]-Table1[[#This Row],[expenditure_nominal]] -> 787.18942 | I2: ='Fiscal Gap'!B2/(Table1[[#This Row],[ILNGSP]]) -> 0.071566442 | J2: ='Fiscal Gap'!C2/Table1[[#This Row],[ILNGSP]] -> 0.073369716 | K2: =Table1[[#This Row],[revenue_share_gsp]]-Table1[[#This Row],[expenditure_share_gsp]] -> 0.0018032742 | L2: ='Fiscal Gap'!B2*($C$29/Table1[[#This Row],[CPIAUCSL]]) -> 61534.637 | M2: ='Fiscal Gap'!C2*($C$29/Table1[[#This Row],[CPIAUCSL]]) -> 63085.137 | N2: =Table1[[#This Row],[revenue_adjusted_cpi]]-Table1[[#This Row],[expenditure_adjusted_cpi]] -> 1550.5008 | O2: =Table1[[#This Row],[expenditure_nominal]]/Table1[[#This Row],[ILPOP]]*1000 -> 2588.3784 | P2: =Table1[[#This Row],[revenue_nominal]]/Table1[[#This Row],[ILPOP]]*1000 -> 2653.5983 | Q2: =Table1[[#This Row],[nominal_rev_perperson]]-Table1[[#This Row],[nominal_exp_perperson]] -> 65.219897 | R2: 55.563 | S2: =Table1[[#This Row],[expenditure_nominal]]*($R$29/Table1[[#This Row],[A829RD3Q086SBEA]]) -> 74298.288 | T2: =Table1[[#This Row],[revenue_nominal]]*($R$29/Table1[[#This Row],[A829RD3Q086SBEA]]) -> 76170.397 | U2: =Table1[[#This Row],[rev_adj_sbea]]-Table1[[#This Row],[exp_adj_sbea]] -> 1872.1091
A3: 1999 | B3: 459971.6 | C3: 164.7 | E3: 12128.37 | F3: ='Fiscal Gap'!B3 -> 33845.351 | G3: ='Fiscal Gap'!C3 -> 33963.525 | H3: =Table1[[#This Row],[revenue_nominal]]-Table1[[#This Row],[expenditure_nominal]] -> 118.17437 | I3: ='Fiscal Gap'!B3/(Table1[[#This Row],[ILNGSP]]) -> 0.073581393 | J3: ='Fiscal Gap'!C3/Table1[[#This Row],[ILNGSP]] -> 0.073838309 | K3: =Table1[[#This Row],[revenue_share_gsp]]-Table1[[#This Row],[expenditure_share_gsp]] -> 0.00025691667 | L3: ='Fiscal Gap'!B3*($C$29/Table1[[#This Row],[CPIAUCSL]]) -> 65571.206 | M3: ='Fiscal Gap'!C3*($C$29/Table1[[#This Row],[CPIAUCSL]]) -> 65800.154 | N3: =Table1[[#This Row],[revenue_adjusted_cpi]]-Table1[[#This Row],[expenditure_adjusted_cpi]] -> 228.94831 | O3: =Table1[[#This Row],[expenditure_nominal]]/Table1[[#This Row],[ILPOP]]*1000 -> 2790.5935 | P3: =Table1[[#This Row],[revenue_nominal]]/Table1[[#This Row],[ILPOP]]*1000 -> 2800.3372 | Q3: =Table1[[#This Row],[nominal_rev_perperson]]-Table1[[#This Row],[nominal_exp_perperson]] -> 9.7436317 | R3: 57.127 | S3: =Table1[[#This Row],[expenditure_nominal]]*($R$29/Table1[[#This Row],[A829RD3Q086SBEA]]) -> 78287.999 | T3: =Table1[[#This Row],[revenue_nominal]]*($R$29/Table1[[#This Row],[A829RD3Q086SBEA]]) -> 78561.349 | U3: =Table1[[#This Row],[rev_adj_sbea]]-Table1[[#This Row],[exp_adj_sbea]] -> 273.35025
A4: 2000 | B4: 486089.7 | C4: 169.3 | E4: 12434.161 | F4: ='Fiscal Gap'!B4 -> 37340.66 | G4: ='Fiscal Gap'!C4 -> 37041.392 | H4: =Table1[[#This Row],[revenue_nominal]]-Table1[[#This Row],[expenditure_nominal]] -> -299.26879 | I4: ='Fiscal Gap'!B4/(Table1[[#This Row],[ILNGSP]]) -> 0.076818456 | J4: ='Fiscal Gap'!C4/Table1[[#This Row],[ILNGSP]] -> 0.076202791 | K4: =Table1[[#This Row],[revenue_share_gsp]]-Table1[[#This Row],[expenditure_share_gsp]] -> -0.00061566577 | L4: ='Fiscal Gap'!B4*($C$29/Table1[[#This Row],[CPIAUCSL]]) -> 70377.33 | M4: ='Fiscal Gap'!C4*($C$29/Table1[[#This Row],[CPIAUCSL]]) -> 69813.287 | N4: =Table1[[#This Row],[revenue_adjusted_cpi]]-Table1[[#This Row],[expenditure_adjusted_cpi]] -> -564.04301 | O4: =Table1[[#This Row],[expenditure_nominal]]/Table1[[#This Row],[ILPOP]]*1000 -> 3003.0704 | P4: =Table1[[#This Row],[revenue_nominal]]/Table1[[#This Row],[ILPOP]]*1000 -> 2979.0021 | Q4: =Table1[[#This Row],[nominal_rev_perperson]]-Table1[[#This Row],[nominal_exp_perperson]] -> -24.068274 | R4: 60.029 | S4: =Table1[[#This Row],[expenditure_nominal]]*($R$29/Table1[[#This Row],[A829RD3Q086SBEA]]) -> 82197.475 | T4: =Table1[[#This Row],[revenue_nominal]]*($R$29/Table1[[#This Row],[A829RD3Q086SBEA]]) -> 81538.699 | U4: =Table1[[#This Row],[rev_adj_sbea]]-Table1[[#This Row],[exp_adj_sbea]] -> -658.77622
A5: 2001 | B5: 499618.4 | C5: 175.6 | E5: 12488.445 | F5: ='Fiscal Gap'!B5 -> 40354.009 | G5: ='Fiscal Gap'!C5 -> 38278.701 | H5: =Table1[[#This Row],[revenue_nominal]]-Table1[[#This Row],[expenditure_nominal]] -> -2075.3084 | I5: ='Fiscal Gap'!B5/(Table1[[#This Row],[ILNGSP]]) -> 0.080769661 | J5: ='Fiscal Gap'!C5/Table1[[#This Row],[ILNGSP]] -> 0.076615874 | K5: =Table1[[#This Row],[revenue_share_gsp]]-Table1[[#This Row],[expenditure_share_gsp]] -> -0.004153787 | L5: ='Fiscal Gap'!B5*($C$29/Table1[[#This Row],[CPIAUCSL]]) -> 73328.014 | M5: ='Fiscal Gap'!C5*($C$29/Table1[[#This Row],[CPIAUCSL]]) -> 69556.933 | N5: =Table1[[#This Row],[revenue_adjusted_cpi]]-Table1[[#This Row],[expenditure_adjusted_cpi]] -> -3771.0813 | O5: =Table1[[#This Row],[expenditure_nominal]]/Table1[[#This Row],[ILPOP]]*1000 -> 3231.3077 | P5: =Table1[[#This Row],[revenue_nominal]]/Table1[[#This Row],[ILPOP]]*1000 -> 3065.1295 | Q5: =Table1[[#This Row],[nominal_rev_perperson]]-Table1[[#This Row],[nominal_exp_perperson]] -> -166.17829 | R5: 62.83 | S5: =Table1[[#This Row],[expenditure_nominal]]*($R$29/Table1[[#This Row],[A829RD3Q086SBEA]]) -> 84870.589 | T5: =Table1[[#This Row],[revenue_nominal]]*($R$29/Table1[[#This Row],[A829RD3Q086SBEA]]) -> 80505.901 | U5: =Table1[[#This Row],[rev_adj_sbea]]-Table1[[#This Row],[exp_adj_sbea]] -> -4364.6878
A6: 2002 | B6: 511485.9 | C6: 177.7 | E6: 12525.556 | F6: ='Fiscal Gap'!B6 -> 42063.831 | G6: ='Fiscal Gap'!C6 -> 37919.379 | H6: =Table1[[#This Row],[revenue_nominal]]-Table1[[#This Row],[expenditure_nominal]] -> -4144.4515 | I6: ='Fiscal Gap'!B6/(Table1[[#This Row],[ILNGSP]]) -> 0.082238495 | J6: ='Fiscal Gap'!C6/Table1[[#This Row],[ILNGSP]] -> 0.074135728 | K6: =Table1[[#This Row],[revenue_share_gsp]]-Table1[[#This Row],[expenditure_share_gsp]] -> -0.0081027678 | L6: ='Fiscal Gap'!B6*($C$29/Table1[[#This Row],[CPIAUCSL]]) -> 75531.68 | M6: ='Fiscal Gap'!C6*($C$29/Table1[[#This Row],[CPIAUCSL]]) -> 68089.719 | N6: =Table1[[#This Row],[revenue_adjusted_cpi]]-Table1[[#This Row],[expenditure_adjusted_cpi]] -> -7441.9609 | O6: =Table1[[#This Row],[expenditure_nominal]]/Table1[[#This Row],[ILPOP]]*1000 -> 3358.2406 | P6: =Table1[[#This Row],[revenue_nominal]]/Table1[[#This Row],[ILPOP]]*1000 -> 3027.361 | Q6: =Table1[[#This Row],[nominal_rev_perperson]]-Table1[[#This Row],[nominal_exp_perperson]] -> -330.87964 | R6: 63.734 | S6: =Table1[[#This Row],[expenditure_nominal]]*($R$29/Table1[[#This Row],[A829RD3Q086SBEA]]) -> 87211.797 | T6: =Table1[[#This Row],[revenue_nominal]]*($R$29/Table1[[#This Row],[A829RD3Q086SBEA]]) -> 78619.021 | U6: =Table1[[#This Row],[rev_adj_sbea]]-Table1[[#This Row],[exp_adj_sbea]] -> -8592.7757
A7: 2003 | B7: 528577 | C7: 182.6 | E7: 12556.006 | F7: ='Fiscal Gap'!B7 -> 42608.364 | G7: ='Fiscal Gap'!C7 -> 38449.202 | H7: =Table1[[#This Row],[revenue_nominal]]-Table1[[#This Row],[expenditure_nominal]] -> -4159.1624 | I7: ='Fiscal Gap'!B7/(Table1[[#This Row],[ILNGSP]]) -> 0.080609569 | J7: ='Fiscal Gap'!C7/Table1[[#This Row],[ILNGSP]] -> 0.072740966 | K7: =Table1[[#This Row],[revenue_share_gsp]]-Table1[[#This Row],[expenditure_share_gsp]] -> -0.0078686028 | L7: ='Fiscal Gap'!B7*($C$29/Table1[[#This Row],[CPIAUCSL]]) -> 74456.366 | M7: ='Fiscal Gap'!C7*($C$29/Table1[[#This Row],[CPIAUCSL]]) -> 67188.401 | N7: =Table1[[#This Row],[revenue_adjusted_cpi]]-Table1[[#This Row],[expenditure_adjusted_cpi]] -> -7267.9655 | O7: =Table1[[#This Row],[expenditure_nominal]]/Table1[[#This Row],[ILPOP]]*1000 -> 3393.4648 | P7: =Table1[[#This Row],[revenue_nominal]]/Table1[[#This Row],[ILPOP]]*1000 -> 3062.2159 | Q7: =Table1[[#This Row],[nominal_rev_perperson]]-Table1[[#This Row],[nominal_exp_perperson]] -> -331.24884 | R7: 66.256 | S7: =Table1[[#This Row],[expenditure_nominal]]*($R$29/Table1[[#This Row],[A829RD3Q086SBEA]]) -> 84978.143 | T7: =Table1[[#This Row],[revenue_nominal]]*($R$29/Table1[[#This Row],[A829RD3Q086SBEA]]) -> 76683.107 | U7: =Table1[[#This Row],[rev_adj_sbea]]-Table1[[#This Row],[exp_adj_sbea]] -> -8295.0357
A8: 2004 | B8: 560079.8 | C8: 186.3 | E8: 12589.773 | F8: ='Fiscal Gap'!B8 -> 53019.315 | G8: ='Fiscal Gap'!C8 -> 42605.136 | H8: =Table1[[#This Row],[revenue_nominal]]-Table1[[#This Row],[expenditure_nominal]] -> -10414.179 | I8: ='Fiscal Gap'!B8/(Table1[[#This Row],[ILNGSP]]) -> 0.094663859 | J8: ='Fiscal Gap'!C8/Table1[[#This Row],[ILNGSP]] -> 0.07606976 | K8: =Table1[[#This Row],[revenue_share_gsp]]-Table1[[#This Row],[expenditure_share_gsp]] -> -0.018594099 | L8: ='Fiscal Gap'!B8*($C$29/Table1[[#This Row],[CPIAUCSL]]) -> 90809.024 | M8: ='Fiscal Gap'!C8*($C$29/Table1[[#This Row],[CPIAUCSL]]) -> 72972.101 | N8: =Table1[[#This Row],[revenue_adjusted_cpi]]-Table1[[#This Row],[expenditure_adjusted_cpi]] -> -17836.923 | O8: =Table1[[#This Row],[expenditure_nominal]]/Table1[[#This Row],[ILPOP]]*1000 -> 4211.3003 | P8: =Table1[[#This Row],[revenue_nominal]]/Table1[[#This Row],[ILPOP]]*1000 -> 3384.1068 | Q8: =Table1[[#This Row],[nominal_rev_perperson]]-Table1[[#This Row],[nominal_exp_perperson]] -> -827.19356 | R8: 68.132 | S8: =Table1[[#This Row],[expenditure_nominal]]*($R$29/Table1[[#This Row],[A829RD3Q086SBEA]]) -> 102830.17 | T8: =Table1[[#This Row],[revenue_nominal]]*($R$29/Table1[[#This Row],[A829RD3Q086SBEA]]) -> 82632.027 | U8: =Table1[[#This Row],[rev_adj_sbea]]-Table1[[#This Row],[exp_adj_sbea]] -> -20198.146
A9: 2005 | B9: 589153.7 | C9: 191.6 | E9: 12609.903 | F9: ='Fiscal Gap'!B9 -> 45358.95 | G9: ='Fiscal Gap'!C9 -> 44301.936 | H9: =Table1[[#This Row],[revenue_nominal]]-Table1[[#This Row],[expenditure_nominal]] -> -1057.0148 | I9: ='Fiscal Gap'!B9/(Table1[[#This Row],[ILNGSP]]) -> 0.076990012 | J9: ='Fiscal Gap'!C9/Table1[[#This Row],[ILNGSP]] -> 0.075195888 | K9: =Table1[[#This Row],[revenue_share_gsp]]-Table1[[#This Row],[expenditure_share_gsp]] -> -0.001794124 | L9: ='Fiscal Gap'!B9*($C$29/Table1[[#This Row],[CPIAUCSL]]) -> 75539.698 | M9: ='Fiscal Gap'!C9*($C$29/Table1[[#This Row],[CPIAUCSL]]) -> 73779.371 | N9: =Table1[[#This Row],[revenue_adjusted_cpi]]-Table1[[#This Row],[expenditure_adjusted_cpi]] -> -1760.3269 | O9: =Table1[[#This Row],[expenditure_nominal]]/Table1[[#This Row],[ILPOP]]*1000 -> 3597.0896 | P9: =Table1[[#This Row],[revenue_nominal]]/Table1[[#This Row],[ILPOP]]*1000 -> 3513.2654 | Q9: =Table1[[#This Row],[nominal_rev_perperson]]-Table1[[#This Row],[nominal_exp_perperson]] -> -83.824183 | R9: 72.087 | S9: =Table1[[#This Row],[expenditure_nominal]]*($R$29/Table1[[#This Row],[A829RD3Q086SBEA]]) -> 83146.435 | T9: =Table1[[#This Row],[revenue_nominal]]*($R$29/Table1[[#This Row],[A829RD3Q086SBEA]]) -> 81208.846 | U9: =Table1[[#This Row],[rev_adj_sbea]]-Table1[[#This Row],[exp_adj_sbea]] -> -1937.5892
A10: 2006 | B10: 624068.1 | C10: 199.3 | E10: 12643.955 | F10: ='Fiscal Gap'!B10 -> 48059.471 | G10: ='Fiscal Gap'!C10 -> 46165.606 | H10: =Table1[[#This Row],[revenue_nominal]]-Table1[[#This Row],[expenditure_nominal]] -> -1893.8646 | I10: ='Fiscal Gap'!B10/(Table1[[#This Row],[ILNGSP]]) -> 0.077009979 | J10: ='Fiscal Gap'!C10/Table1[[#This Row],[ILNGSP]] -> 0.07397527 | K10: =Table1[[#This Row],[revenue_share_gsp]]-Table1[[#This Row],[expenditure_share_gsp]] -> -0.0030347083 | L10: ='Fiscal Gap'!B10*($C$29/Table1[[#This Row],[CPIAUCSL]]) -> 76944.829 | M10: ='Fiscal Gap'!C10*($C$29/Table1[[#This Row],[CPIAUCSL]]) -> 73912.688 | N10: =Table1[[#This Row],[revenue_adjusted_cpi]]-Table1[[#This Row],[expenditure_adjusted_cpi]] -> -3032.1409 | O10: =Table1[[#This Row],[expenditure_nominal]]/Table1[[#This Row],[ILPOP]]*1000 -> 3800.984 | P10: =Table1[[#This Row],[revenue_nominal]]/Table1[[#This Row],[ILPOP]]*1000 -> 3651.1998 | Q10: =Table1[[#This Row],[nominal_rev_perperson]]-Table1[[#This Row],[nominal_exp_perperson]] -> -149.7842 | R10: 75.926 | S10: =Table1[[#This Row],[expenditure_nominal]]*($R$29/Table1[[#This Row],[A829RD3Q086SBEA]]) -> 83642.317 | T10: =Table1[[#This Row],[revenue_nominal]]*($R$29/Table1[[#This Row],[A829RD3Q086SBEA]]) -> 80346.25 | U10: =Table1[[#This Row],[rev_adj_sbea]]-Table1[[#This Row],[exp_adj_sbea]] -> -3296.0668
A11: 2007 | B11: 649307.4 | C11: 203.437 | E11: 12695.866 | F11: ='Fiscal Gap'!B11 -> 51127.601 | G11: ='Fiscal Gap'!C11 -> 49489.711 | H11: =Table1[[#This Row],[revenue_nominal]]-Table1[[#This Row],[expenditure_nominal]] -> -1637.8898 | I11: ='Fiscal Gap'!B11/(Table1[[#This Row],[ILNGSP]]) -> 0.078741749 | J11: ='Fiscal Gap'!C11/Table1[[#This Row],[ILNGSP]] -> 0.076219231 | K11: =Table1[[#This Row],[revenue_share_gsp]]-Table1[[#This Row],[expenditure_share_gsp]] -> -0.0025225183 | L11: ='Fiscal Gap'!B11*($C$29/Table1[[#This Row],[CPIAUCSL]]) -> 80192.401 | M11: ='Fiscal Gap'!C11*($C$29/Table1[[#This Row],[CPIAUCSL]]) -> 77623.411 | N11: =Table1[[#This Row],[revenue_adjusted_cpi]]-Table1[[#This Row],[expenditure_adjusted_cpi]] -> -2568.9904 | O11: =Table1[[#This Row],[expenditure_nominal]]/Table1[[#This Row],[ILPOP]]*1000 -> 4027.1062 | P11: =Table1[[#This Row],[revenue_nominal]]/Table1[[#This Row],[ILPOP]]*1000 -> 3898.0965 | Q11: =Table1[[#This Row],[nominal_rev_perperson]]-Table1[[#This Row],[nominal_exp_perperson]] -> -129.00969 | R11: 80.209 | S11: =Table1[[#This Row],[expenditure_nominal]]*($R$29/Table1[[#This Row],[A829RD3Q086SBEA]]) -> 84230.601 | T11: =Table1[[#This Row],[revenue_nominal]]*($R$29/Table1[[#This Row],[A829RD3Q086SBEA]]) -> 81532.245 | U11: =Table1[[#This Row],[rev_adj_sbea]]-Table1[[#This Row],[exp_adj_sbea]] -> -2698.3555
A12: 2008 | B12: 649677.3 | C12: 212.174 | E12: 12747.038 | F12: ='Fiscal Gap'!B12 -> 54169.864 | G12: ='Fiscal Gap'!C12 -> 51636.909 | H12: =Table1[[#This Row],[revenue_nominal]]-Table1[[#This Row],[expenditure_nominal]] -> -2532.9557 | I12: ='Fiscal Gap'!B12/(Table1[[#This Row],[ILNGSP]]) -> 0.083379648 | J12: ='Fiscal Gap'!C12/Table1[[#This Row],[ILNGSP]] -> 0.079480857 | K12: =Table1[[#This Row],[revenue_share_gsp]]-Table1[[#This Row],[expenditure_share_gsp]] -> -0.0038987905 | L12: ='Fiscal Gap'!B12*($C$29/Table1[[#This Row],[CPIAUCSL]]) -> 81465.426 | M12: ='Fiscal Gap'!C12*($C$29/Table1[[#This Row],[CPIAUCSL]]) -> 77656.144 | N12: =Table1[[#This Row],[revenue_adjusted_cpi]]-Table1[[#This Row],[expenditure_adjusted_cpi]] -> -3809.2824 | O12: =Table1[[#This Row],[expenditure_nominal]]/Table1[[#This Row],[ILPOP]]*1000 -> 4249.6041 | P12: =Table1[[#This Row],[revenue_nominal]]/Table1[[#This Row],[ILPOP]]*1000 -> 4050.8947 | Q12: =Table1[[#This Row],[nominal_rev_perperson]]-Table1[[#This Row],[nominal_exp_perperson]] -> -198.70935 | R12: 84.484 | S12: =Table1[[#This Row],[expenditure_nominal]]*($R$29/Table1[[#This Row],[A829RD3Q086SBEA]]) -> 84726.813 | T12: =Table1[[#This Row],[revenue_nominal]]*($R$29/Table1[[#This Row],[A829RD3Q086SBEA]]) -> 80765.03 | U12: =Table1[[#This Row],[rev_adj_sbea]]-Table1[[#This Row],[exp_adj_sbea]] -> -3961.7832
A13: 2009 | B13: 645843.2 | C13: 211.933 | E13: 12796.778 | F13: ='Fiscal Gap'!B13 -> 56749.683 | G13: ='Fiscal Gap'!C13 -> 51460.959 | H13: =Table1[[#This Row],[revenue_nominal]]-Table1[[#This Row],[expenditure_nominal]] -> -5288.7246 | I13: ='Fiscal Gap'!B13/(Table1[[#This Row],[ILNGSP]]) -> 0.087869135 | J13: ='Fiscal Gap'!C13/Table1[[#This Row],[ILNGSP]] -> 0.079680267 | K13: =Table1[[#This Row],[revenue_share_gsp]]-Table1[[#This Row],[expenditure_share_gsp]] -> -0.0081888679 | L13: ='Fiscal Gap'!B13*($C$29/Table1[[#This Row],[CPIAUCSL]]) -> 85442.236 | M13: ='Fiscal Gap'!C13*($C$29/Table1[[#This Row],[CPIAUCSL]]) -> 77479.541 | N13: =Table1[[#This Row],[revenue_adjusted_cpi]]-Table1[[#This Row],[expenditure_adjusted_cpi]] -> -7962.6957 | O13: =Table1[[#This Row],[expenditure_nominal]]/Table1[[#This Row],[ILPOP]]*1000 -> 4434.6853 | P13: =Table1[[#This Row],[revenue_nominal]]/Table1[[#This Row],[ILPOP]]*1000 -> 4021.3997 | Q13: =Table1[[#This Row],[nominal_rev_perperson]]-Table1[[#This Row],[nominal_exp_perperson]] -> -413.28564 | R13: 84.679 | S13: =Table1[[#This Row],[expenditure_nominal]]*($R$29/Table1[[#This Row],[A829RD3Q086SBEA]]) -> 88557.492 | T13: =Table1[[#This Row],[revenue_nominal]]*($R$29/Table1[[#This Row],[A829RD3Q086SBEA]]) -> 80304.474 | U13: =Table1[[#This Row],[rev_adj_sbea]]-Table1[[#This Row],[exp_adj_sbea]] -> -8253.0186
... A19: 2015 | B19: 802592 | C19: 234.747 | E19: 12859.585 | F19: ='Fiscal Gap'!B19 -> 69937.377 | G19: ='Fiscal Gap'!C19 -> 66584.604 | H19: =Table1[[#This Row],[revenue_nominal]]-Table1[[#This Row],[expenditure_nominal]] -> -3352.7729 | I19: ='Fiscal Gap'!B19/(Table1[[#This Row],[ILNGSP]]) -> 0.087139389 | J19: ='Fiscal Gap'!C19/Table1[[#This Row],[ILNGSP]] -> 0.082961958 | K19: =Table1[[#This Row],[revenue_share_gsp]]-Table1[[#This Row],[expenditure_share_gsp]] -> -0.0041774312 | L19: ='Fiscal Gap'!B19*($C$29/Table1[[#This Row],[CPIAUCSL]]) -> 95064.208 | M19: ='Fiscal Gap'!C19*($C$29/Table1[[#This Row],[CPIAUCSL]]) -> 90506.864 | N19: =Table1[[#This Row],[revenue_adjusted_cpi]]-Table1[[#This Row],[expenditure_adjusted_cpi]] -> -4557.3442 | O19: =Table1[[#This Row],[expenditure_nominal]]/Table1[[#This Row],[ILPOP]]*1000 -> 5438.5407 | P19: =Table1[[#This Row],[revenue_nominal]]/Table1[[#This Row],[ILPOP]]*1000 -> 5177.819 | Q19: =Table1[[#This Row],[nominal_rev_perperson]]-Table1[[#This Row],[nominal_exp_perperson]] -> -260.7217 | R19: 97.172 | S19: =Table1[[#This Row],[expenditure_nominal]]*($R$29/Table1[[#This Row],[A829RD3Q086SBEA]]) -> 95105.533 | T19: =Table1[[#This Row],[revenue_nominal]]*($R$29/Table1[[#This Row],[A829RD3Q086SBEA]]) -> 90546.208 | U19: =Table1[[#This Row],[rev_adj_sbea]]-Table1[[#This Row],[exp_adj_sbea]] -> -4559.3253
A20: 2016 | B20: 813561.6 | C20: 237.652 | D20: 98.4 | E20: 12821.709 | F20: ='Fiscal Gap'!B20 -> 63928.13 | G20: ='Fiscal Gap'!C20 -> 64148.842 | H20: =Table1[[#This Row],[revenue_nominal]]-Table1[[#This Row],[expenditure_nominal]] -> 220.71186 | I20: ='Fiscal Gap'!B20/(Table1[[#This Row],[ILNGSP]]) -> 0.078578107 | J20: ='Fiscal Gap'!C20/Table1[[#This Row],[ILNGSP]] -> 0.078849398 | K20: =Table1[[#This Row],[revenue_share_gsp]]-Table1[[#This Row],[expenditure_share_gsp]] -> 0.0002712909 | L20: ='Fiscal Gap'!B20*($C$29/Table1[[#This Row],[CPIAUCSL]]) -> 85833.788 | M20: ='Fiscal Gap'!C20*($C$29/Table1[[#This Row],[CPIAUCSL]]) -> 86130.129 | N20: =Table1[[#This Row],[revenue_adjusted_cpi]]-Table1[[#This Row],[expenditure_adjusted_cpi]] -> 296.34114 | O20: =Table1[[#This Row],[expenditure_nominal]]/Table1[[#This Row],[ILPOP]]*1000 -> 4985.929 | P20: =Table1[[#This Row],[revenue_nominal]]/Table1[[#This Row],[ILPOP]]*1000 -> 5003.1429 | Q20: =Table1[[#This Row],[nominal_rev_perperson]]-Table1[[#This Row],[nominal_exp_perperson]] -> 17.213919 | R20: 96.683 | S20: =Table1[[#This Row],[expenditure_nominal]]*($R$29/Table1[[#This Row],[A829RD3Q086SBEA]]) -> 87373.448 | T20: =Table1[[#This Row],[revenue_nominal]]*($R$29/Table1[[#This Row],[A829RD3Q086SBEA]]) -> 87675.105 | U20: =Table1[[#This Row],[rev_adj_sbea]]-Table1[[#This Row],[exp_adj_sbea]] -> 301.65682 | V20: =Table1[[#This Row],[expenditure_nominal]]*($D$29/Table1[[#This Row],[WPSFD49406]]) -> 88595.683 | W20: =Table1[[#This Row],[revenue_nominal]]*($D$29/Table1[[#This Row],[WPSFD49406]]) -> 88901.56
A21: 2017 | B21: 832826.8 | C21: 243.618 | D21: 100.3 | E21: 12779.893 | F21: ='Fiscal Gap'!B21 -> 71724.19 | G21: ='Fiscal Gap'!C21 -> 63653.855 | H21: =Table1[[#This Row],[revenue_nominal]]-Table1[[#This Row],[expenditure_nominal]] -> -8070.3355 | I21: ='Fiscal Gap'!B21/(Table1[[#This Row],[ILNGSP]]) -> 0.086121377 | J21: ='Fiscal Gap'!C21/Table1[[#This Row],[ILNGSP]] -> 0.076431084 | K21: =Table1[[#This Row],[revenue_share_gsp]]-Table1[[#This Row],[expenditure_share_gsp]] -> -0.0096902928 | L21: ='Fiscal Gap'!B21*($C$29/Table1[[#This Row],[CPIAUCSL]]) -> 93942.915 | M21: ='Fiscal Gap'!C21*($C$29/Table1[[#This Row],[CPIAUCSL]]) -> 83372.55 | N21: =Table1[[#This Row],[revenue_adjusted_cpi]]-Table1[[#This Row],[expenditure_adjusted_cpi]] -> -10570.365 | O21: =Table1[[#This Row],[expenditure_nominal]]/Table1[[#This Row],[ILPOP]]*1000 -> 5612.2685 | P21: =Table1[[#This Row],[revenue_nominal]]/Table1[[#This Row],[ILPOP]]*1000 -> 4980.7815 | Q21: =Table1[[#This Row],[nominal_rev_perperson]]-Table1[[#This Row],[nominal_exp_perperson]] -> -631.48694 | R21: 99.101 | S21: =Table1[[#This Row],[expenditure_nominal]]*($R$29/Table1[[#This Row],[A829RD3Q086SBEA]]) -> 95636.838 | T21: =Table1[[#This Row],[revenue_nominal]]*($R$29/Table1[[#This Row],[A829RD3Q086SBEA]]) -> 84875.875 | U21: =Table1[[#This Row],[rev_adj_sbea]]-Table1[[#This Row],[exp_adj_sbea]] -> -10760.963 | V21: =Table1[[#This Row],[expenditure_nominal]]*($D$29/Table1[[#This Row],[WPSFD49406]]) -> 97517.01 | W21: =Table1[[#This Row],[revenue_nominal]]*($D$29/Table1[[#This Row],[WPSFD49406]]) -> 86544.492
A22: 2018 | B22: 871024.2 | C22: 248.859 | D22: 103.8 | E22: 12724.685 | F22: ='Fiscal Gap'!B22 -> 74966.128 | G22: ='Fiscal Gap'!C22 -> 73008.551 | H22: =Table1[[#This Row],[revenue_nominal]]-Table1[[#This Row],[expenditure_nominal]] -> -1957.576 | I22: ='Fiscal Gap'!B22/(Table1[[#This Row],[ILNGSP]]) -> 0.086066641 | J22: ='Fiscal Gap'!C22/Table1[[#This Row],[ILNGSP]] -> 0.0838192 | K22: =Table1[[#This Row],[revenue_share_gsp]]-Table1[[#This Row],[expenditure_share_gsp]] -> -0.0022474416 | L22: ='Fiscal Gap'!B22*($C$29/Table1[[#This Row],[CPIAUCSL]]) -> 96121.265 | M22: ='Fiscal Gap'!C22*($C$29/Table1[[#This Row],[CPIAUCSL]]) -> 93611.268 | N22: =Table1[[#This Row],[revenue_adjusted_cpi]]-Table1[[#This Row],[expenditure_adjusted_cpi]] -> -2509.9961 | O22: =Table1[[#This Row],[expenditure_nominal]]/Table1[[#This Row],[ILPOP]]*1000 -> 5891.3936 | P22: =Table1[[#This Row],[revenue_nominal]]/Table1[[#This Row],[ILPOP]]*1000 -> 5737.5528 | Q22: =Table1[[#This Row],[nominal_rev_perperson]]-Table1[[#This Row],[nominal_exp_perperson]] -> -153.84083 | R22: 102.756 | S22: =Table1[[#This Row],[expenditure_nominal]]*($R$29/Table1[[#This Row],[A829RD3Q086SBEA]]) -> 96404.094 | T22: =Table1[[#This Row],[revenue_nominal]]*($R$29/Table1[[#This Row],[A829RD3Q086SBEA]]) -> 93886.712 | U22: =Table1[[#This Row],[rev_adj_sbea]]-Table1[[#This Row],[exp_adj_sbea]] -> -2517.3815 | V22: =Table1[[#This Row],[expenditure_nominal]]*($D$29/Table1[[#This Row],[WPSFD49406]]) -> 98488.014 | W22: =Table1[[#This Row],[revenue_nominal]]*($D$29/Table1[[#This Row],[WPSFD49406]]) -> 95916.215
A23: 2019 | B23: 895601.8 | C23: 252.561 | D23: 105.5 | E23: 12667.017 | F23: ='Fiscal Gap'!B23 -> 74401.847 | G23: ='Fiscal Gap'!C23 -> 74631.657 | H23: =Table1[[#This Row],[revenue_nominal]]-Table1[[#This Row],[expenditure_nominal]] -> 229.81077 | I23: ='Fiscal Gap'!B23/(Table1[[#This Row],[ILNGSP]]) -> 0.083074695 | J23: ='Fiscal Gap'!C23/Table1[[#This Row],[ILNGSP]] -> 0.083331295 | K23: =Table1[[#This Row],[revenue_share_gsp]]-Table1[[#This Row],[expenditure_share_gsp]] -> 0.00025659928 | L23: ='Fiscal Gap'!B23*($C$29/Table1[[#This Row],[CPIAUCSL]]) -> 93999.421 | M23: ='Fiscal Gap'!C23*($C$29/Table1[[#This Row],[CPIAUCSL]]) -> 94289.764 | N23: =Table1[[#This Row],[revenue_adjusted_cpi]]-Table1[[#This Row],[expenditure_adjusted_cpi]] -> 290.34333 | O23: =Table1[[#This Row],[expenditure_nominal]]/Table1[[#This Row],[ILPOP]]*1000 -> 5873.6675 | P23: =Table1[[#This Row],[revenue_nominal]]/Table1[[#This Row],[ILPOP]]*1000 -> 5891.81 | Q23: =Table1[[#This Row],[nominal_rev_perperson]]-Table1[[#This Row],[nominal_exp_perperson]] -> 18.142454 | R23: 104.676 | S23: =Table1[[#This Row],[expenditure_nominal]]*($R$29/Table1[[#This Row],[A829RD3Q086SBEA]]) -> 93923.482 | T23: =Table1[[#This Row],[revenue_nominal]]*($R$29/Table1[[#This Row],[A829RD3Q086SBEA]]) -> 94213.591 | U23: =Table1[[#This Row],[rev_adj_sbea]]-Table1[[#This Row],[exp_adj_sbea]] -> 290.10877 | V23: =Table1[[#This Row],[expenditure_nominal]]*($D$29/Table1[[#This Row],[WPSFD49406]]) -> 96171.615 | W23: =Table1[[#This Row],[revenue_nominal]]*($D$29/Table1[[#This Row],[WPSFD49406]]) -> 96468.668
A24: 2020 | B24: 860807.8 | C24: 259.127 | D24: 107.5 | E24: 12799.088 | F24: ='Fiscal Gap'!B24 -> 81603.229 | G24: ='Fiscal Gap'!C24 -> 80582.05 | H24: =Table1[[#This Row],[revenue_nominal]]-Table1[[#This Row],[expenditure_nominal]] -> -1021.1793 | I24: ='Fiscal Gap'!B24/(Table1[[#This Row],[ILNGSP]]) -> 0.094798432 | J24: ='Fiscal Gap'!C24/Table1[[#This Row],[ILNGSP]] -> 0.093612128 | K24: =Table1[[#This Row],[revenue_share_gsp]]-Table1[[#This Row],[expenditure_share_gsp]] -> -0.0011863035 | L24: ='Fiscal Gap'!B24*($C$29/Table1[[#This Row],[CPIAUCSL]]) -> 100485.28 | M24: ='Fiscal Gap'!C24*($C$29/Table1[[#This Row],[CPIAUCSL]]) -> 99227.807 | N24: =Table1[[#This Row],[revenue_adjusted_cpi]]-Table1[[#This Row],[expenditure_adjusted_cpi]] -> -1257.4685 | O24: =Table1[[#This Row],[expenditure_nominal]]/Table1[[#This Row],[ILPOP]]*1000 -> 6375.7066 | P24: =Table1[[#This Row],[revenue_nominal]]/Table1[[#This Row],[ILPOP]]*1000 -> 6295.9212 | Q24: =Table1[[#This Row],[nominal_rev_perperson]]-Table1[[#This Row],[nominal_exp_perperson]] -> -79.785321 | R24: 107.818 | S24: =Table1[[#This Row],[expenditure_nominal]]*($R$29/Table1[[#This Row],[A829RD3Q086SBEA]]) -> 100012.36 | T24: =Table1[[#This Row],[revenue_nominal]]*($R$29/Table1[[#This Row],[A829RD3Q086SBEA]]) -> 98760.807 | U24: =Table1[[#This Row],[rev_adj_sbea]]-Table1[[#This Row],[exp_adj_sbea]] -> -1251.5504 | V24: =Table1[[#This Row],[expenditure_nominal]]*($D$29/Table1[[#This Row],[WPSFD49406]]) -> 103517.68 | W24: =Table1[[#This Row],[revenue_nominal]]*($D$29/Table1[[#This Row],[WPSFD49406]]) -> 102222.27
A25: 2021 | B25: 947223.9 | C25: 262.639 | D25: 108.9 | E25: 12700.641 | F25: ='Fiscal Gap'!B25 -> 92883.164 | G25: ='Fiscal Gap'!C25 -> 95200.509 | H25: =Table1[[#This Row],[revenue_nominal]]-Table1[[#This Row],[expenditure_nominal]] -> 2317.3449 | I25: ='Fiscal Gap'!B25/(Table1[[#This Row],[ILNGSP]]) -> 0.098058299 | J25: ='Fiscal Gap'!C25/Table1[[#This Row],[ILNGSP]] -> 0.10050476 | K25: =Table1[[#This Row],[revenue_share_gsp]]-Table1[[#This Row],[expenditure_share_gsp]] -> 0.0024464595 | L25: ='Fiscal Gap'!B25*($C$29/Table1[[#This Row],[CPIAUCSL]]) -> 112845.84 | M25: ='Fiscal Gap'!C25*($C$29/Table1[[#This Row],[CPIAUCSL]]) -> 115661.23 | N25: =Table1[[#This Row],[revenue_adjusted_cpi]]-Table1[[#This Row],[expenditure_adjusted_cpi]] -> 2815.3942 | O25: =Table1[[#This Row],[expenditure_nominal]]/Table1[[#This Row],[ILPOP]]*1000 -> 7313.2658 | P25: =Table1[[#This Row],[revenue_nominal]]/Table1[[#This Row],[ILPOP]]*1000 -> 7495.7247 | Q25: =Table1[[#This Row],[nominal_rev_perperson]]-Table1[[#This Row],[nominal_exp_perperson]] -> 182.45889 | R25: 112.355 | S25: =Table1[[#This Row],[expenditure_nominal]]*($R$29/Table1[[#This Row],[A829RD3Q086SBEA]]) -> 109240.12 | T25: =Table1[[#This Row],[revenue_nominal]]*($R$29/Table1[[#This Row],[A829RD3Q086SBEA]]) -> 111965.56 | U25: =Table1[[#This Row],[rev_adj_sbea]]-Table1[[#This Row],[exp_adj_sbea]] -> 2725.4352 | V25: =Table1[[#This Row],[expenditure_nominal]]*($D$29/Table1[[#This Row],[WPSFD49406]]) -> 116312.07 | W25: =Table1[[#This Row],[revenue_nominal]]*($D$29/Table1[[#This Row],[WPSFD49406]]) -> 119213.94
A26: 2022 | B26: 1037735.9 | C26: 282.542 | D26: 122.42 | E26: 12621.821 | F26: ='Fiscal Gap'!B26 -> 100065.06 | G26: ='Fiscal Gap'!C26 -> 116055.69 | H26: =Table1[[#This Row],[revenue_nominal]]-Table1[[#This Row],[expenditure_nominal]] -> 15990.631 | I26: ='Fiscal Gap'!B26/(Table1[[#This Row],[ILNGSP]]) -> 0.096426321 | J26: ='Fiscal Gap'!C26/Table1[[#This Row],[ILNGSP]] -> 0.11183547 | K26: =Table1[[#This Row],[revenue_share_gsp]]-Table1[[#This Row],[expenditure_share_gsp]] -> 0.015409153 | L26: ='Fiscal Gap'!B26*($C$29/Table1[[#This Row],[CPIAUCSL]]) -> 113007.48 | M26: ='Fiscal Gap'!C26*($C$29/Table1[[#This Row],[CPIAUCSL]]) -> 131066.34 | N26: =Table1[[#This Row],[revenue_adjusted_cpi]]-Table1[[#This Row],[expenditure_adjusted_cpi]] -> 18058.861 | O26: =Table1[[#This Row],[expenditure_nominal]]/Table1[[#This Row],[ILPOP]]*1000 -> 7927.9412 | P26: =Table1[[#This Row],[revenue_nominal]]/Table1[[#This Row],[ILPOP]]*1000 -> 9194.8449 | Q26: =Table1[[#This Row],[nominal_rev_perperson]]-Table1[[#This Row],[nominal_exp_perperson]] -> 1266.9037 | R26: 121.898 | S26: =Table1[[#This Row],[expenditure_nominal]]*($R$29/Table1[[#This Row],[A829RD3Q086SBEA]]) -> 108473.45 | T26: =Table1[[#This Row],[revenue_nominal]]*($R$29/Table1[[#This Row],[A829RD3Q086SBEA]]) -> 125807.76 | U26: =Table1[[#This Row],[rev_adj_sbea]]-Table1[[#This Row],[exp_adj_sbea]] -> 17334.312 | V26: =Table1[[#This Row],[expenditure_nominal]]*($D$29/Table1[[#This Row],[WPSFD49406]]) -> 111466.85 | W26: =Table1[[#This Row],[revenue_nominal]]*($D$29/Table1[[#This Row],[WPSFD49406]]) -> 129279.51
A27: 2023 | B27: 1100794.1 | C27: 300.456 | D27: 132.213 | E27: 12642.259 | F27: ='Fiscal Gap'!B27 -> 111971.77 | G27: ='Fiscal Gap'!C27 -> 111766.07 | H27: =Table1[[#This Row],[revenue_nominal]]-Table1[[#This Row],[expenditure_nominal]] -> -205.70263 | I27: ='Fiscal Gap'!B27/(Table1[[#This Row],[ILNGSP]]) -> 0.10171909 | J27: ='Fiscal Gap'!C27/Table1[[#This Row],[ILNGSP]] -> 0.10153222 | K27: =Table1[[#This Row],[revenue_share_gsp]]-Table1[[#This Row],[expenditure_share_gsp]] -> -0.00018686749 | L27: ='Fiscal Gap'!B27*($C$29/Table1[[#This Row],[CPIAUCSL]]) -> 118914.66 | M27: ='Fiscal Gap'!C27*($C$29/Table1[[#This Row],[CPIAUCSL]]) -> 118696.21 | N27: =Table1[[#This Row],[revenue_adjusted_cpi]]-Table1[[#This Row],[expenditure_adjusted_cpi]] -> -218.45737 | O27: =Table1[[#This Row],[expenditure_nominal]]/Table1[[#This Row],[ILPOP]]*1000 -> 8856.9431 | P27: =Table1[[#This Row],[revenue_nominal]]/Table1[[#This Row],[ILPOP]]*1000 -> 8840.6721 | Q27: =Table1[[#This Row],[nominal_rev_perperson]]-Table1[[#This Row],[nominal_exp_perperson]] -> -16.271034 | R27: 127.366 | S27: =Table1[[#This Row],[expenditure_nominal]]*($R$29/Table1[[#This Row],[A829RD3Q086SBEA]]) -> 116169.63 | T27: =Table1[[#This Row],[revenue_nominal]]*($R$29/Table1[[#This Row],[A829RD3Q086SBEA]]) -> 115956.22 | U27: =Table1[[#This Row],[rev_adj_sbea]]-Table1[[#This Row],[exp_adj_sbea]] -> -213.4145 | V27: =Table1[[#This Row],[expenditure_nominal]]*($D$29/Table1[[#This Row],[WPSFD49406]]) -> 115491.5 | W27: =Table1[[#This Row],[revenue_nominal]]*($D$29/Table1[[#This Row],[WPSFD49406]]) -> 115279.33
A28: 2024 | B28: 1148106.1 | C28: 309.794 | D28: 131.882 | E28: 12710.158 | F28: ='Fiscal Gap'!B28 -> 114997.04 | G28: ='Fiscal Gap'!C28 -> 115121.08 | H28: =Table1[[#This Row],[revenue_nominal]]-Table1[[#This Row],[expenditure_nominal]] -> 124.04716 | I28: ='Fiscal Gap'!B28/(Table1[[#This Row],[ILNGSP]]) -> 0.10016238 | J28: ='Fiscal Gap'!C28/Table1[[#This Row],[ILNGSP]] -> 0.10027042 | K28: =Table1[[#This Row],[revenue_share_gsp]]-Table1[[#This Row],[expenditure_share_gsp]] -> 0.00010804504 | L28: ='Fiscal Gap'!B28*($C$29/Table1[[#This Row],[CPIAUCSL]]) -> 118446.27 | M28: ='Fiscal Gap'!C28*($C$29/Table1[[#This Row],[CPIAUCSL]]) -> 118574.04 | N28: =Table1[[#This Row],[revenue_adjusted_cpi]]-Table1[[#This Row],[expenditure_adjusted_cpi]] -> 127.76785 | O28: =Table1[[#This Row],[expenditure_nominal]]/Table1[[#This Row],[ILPOP]]*1000 -> 9047.6481 | P28: =Table1[[#This Row],[revenue_nominal]]/Table1[[#This Row],[ILPOP]]*1000 -> 9057.4078 | Q28: =Table1[[#This Row],[nominal_rev_perperson]]-Table1[[#This Row],[nominal_exp_perperson]] -> 9.759687 | R28: 129.564 | S28: =Table1[[#This Row],[expenditure_nominal]]*($R$29/Table1[[#This Row],[A829RD3Q086SBEA]]) -> 117284.3 | T28: =Table1[[#This Row],[revenue_nominal]]*($R$29/Table1[[#This Row],[A829RD3Q086SBEA]]) -> 117410.82 | U28: =Table1[[#This Row],[rev_adj_sbea]]-Table1[[#This Row],[exp_adj_sbea]] -> 126.51444 | V28: =Table1[[#This Row],[expenditure_nominal]]*($D$29/Table1[[#This Row],[WPSFD49406]]) -> 118909.56 | W28: =Table1[[#This Row],[revenue_nominal]]*($D$29/Table1[[#This Row],[WPSFD49406]]) -> 119037.83
A29: 2025 | C29: 319.086 | D29: 136.369 | F29: ='Fiscal Gap'!B29 -> 119505.48 | G29: ='Fiscal Gap'!C29 -> 118157.3 | H29: =Table1[[#This Row],[revenue_nominal]]-Table1[[#This Row],[expenditure_nominal]] -> -1348.1887 | L29: ='Fiscal Gap'!B29*($C$29/Table1[[#This Row],[CPIAUCSL]]) -> 119505.48 | M29: ='Fiscal Gap'!C29*($C$29/Table1[[#This Row],[CPIAUCSL]]) -> 118157.3 | N29: =Table1[[#This Row],[revenue_adjusted_cpi]]-Table1[[#This Row],[expenditure_adjusted_cpi]] -> -1348.1887 | O29: =Table1[[#This Row],[expenditure_nominal]]/Table1[[#This Row],[ILPOP]]*1000 -> #DIV/0! | P29: =Table1[[#This Row],[revenue_nominal]]/Table1[[#This Row],[ILPOP]]*1000 -> #DIV/0! | Q29: =Table1[[#This Row],[nominal_rev_perperson]]-Table1[[#This Row],[nominal_exp_perperson]] -> #DIV/0! | R29: 132.141 | S29: =Table1[[#This Row],[expenditure_nominal]]*($R$29/Table1[[#This Row],[A829RD3Q086SBEA]]) -> 119505.48 | T29: =Table1[[#This Row],[revenue_nominal]]*($R$29/Table1[[#This Row],[A829RD3Q086SBEA]]) -> 118157.3 | U29: =Table1[[#This Row],[rev_adj_sbea]]-Table1[[#This Row],[exp_adj_sbea]] -> -1348.1887 | V29: =Table1[[#This Row],[expenditure_nominal]]*($D$29/Table1[[#This Row],[WPSFD49406]]) -> 119505.48 | W29: =Table1[[#This Row],[revenue_nominal]]*($D$29/Table1[[#This Row],[WPSFD49406]]) -> 118157.3

Sheet Fiscal Gap
A1: Year | B1: Expenditures | C1: Revenue | D1: Fiscal Gap
A2: 1998 | B2: 31241.142 | C2: 32028.332 | D2: 787.18942
A3: 1999 | B3: 33845.351 | C3: 33963.525 | D3: 118.17437
A4: 2000 | B4: 37340.66 | C4: 37041.392 | D4: -299.26879
A5: 2001 | B5: 40354.009 | C5: 38278.701 | D5: -2075.3084
A6: 2002 | B6: 42063.831 | C6: 37919.379 | D6: -4144.4515
A7: 2003 | B7: 42608.364 | C7: 38449.202 | D7: -4159.1624
A8: 2004 | B8: 53019.315 | C8: 42605.136 | D8: -10414.179
A9: 2005 | B9: 45358.95 | C9: 44301.936 | D9: -1057.0148
A10: 2006 | B10: 48059.471 | C10: 46165.606 | D10: -1893.8646
A11: 2007 | B11: 51127.601 | C11: 49489.711 | D11: -1637.8898
A12: 2008 | B12: 54169.864 | C12: 51636.909 | D12: -2532.9557
A13: 2009 | B13: 56749.683 | C13: 51460.959 | D13: -5288.7246
... A29: 2025 | B29: 119505.48 | C29: 118157.3 | D29: -1348.1887

Sheet readme
A1: Variable | B1: Full Label | C1: Notes
A2: ILNGSP | B2: Illinois Gross State Product | C2: GSP measured in millions of dollars
A3: CPIAUCSL | B3: Consumer Price Index | C3: To adjust for wages, purchasing power, or cost-of -living expenses
A4: WPSFD49406 | B4: Government Purchases, Non Defense | C4: To adjust revenue for inflation to see "real" production value
A5: ILPOP | B5: State Population (Illinois) | C5: in Thousands of people
A6: Fiscal Gap Tab | B6: Excel Tab: Fiscal Gap Data | C6: Copy/pasted from summary file used to make DataHub
A7: A829RD3Q086SBEA | B7: USBEA | C7: Measures inflation for goods andservices purchased by state and local governments.
A10: Current Label | B10: Suggested Label | C10: Use/Description
A11: Nominal Dollars | B11: no change
A12: Nominal per Person | B12: no change | C12: Measures Illinois’ population in thousands of residents. Adjusting by population shows fiscal totals on a per-person basis.
A13: CPI | B13: Consumer Price Index (CPI) | C13: Consumer Price Index for All Urban Consumers: All Items in U.S. City Average: Measures changes in consumer prices over time. This is a broad inflation adjustment that helps express fiscal totals in real purchasing-power terms (Series identifier CPIAUCSL)
A14: SBEA | B14: State & Local Gov. Price Deflator (S&L IPD) | C14: Implicit Price Deflator for State and Local Government Purchases (S&L IPD): State governments frequently use this specific index to calculate legal funding adjustments, school district spending caps, and local agency budget inflators. Measures price changes for goods and services purchased by governments, excluding defense. This adjustment is useful for approximating how the cost of public-sector purchases changes over time. (Series identifier A829RD3Q086SBEA)
A15: SWPSFD | B15: Producer Price Index (PPI) | C15: Producer Price Index by Commodity: Final Demand: Government Purchases, Nondefense: Measures price changes for goods and services purchased by governments, excluding defense. This adjustment is useful for approximating how the cost of public-sector purchases changes over time. (Series identifier WPSFD49406)
A16: Share GSP% | B16: Share of Illinois Gross State Product (ILGSP) | C16: GSP measures the total value of goods and services produced in Illinois. Adjusting by GSP helps compare fiscal totals relative to the size of the state economy. (Series identifier ILNGSP)
